TEST_Folder/mod10counter.v
//GIVEN CODE OF MOD10COUNTER : 
/*
//four bit mod 10 counter with load//
module mod10counter (clk,rst,count,load,din);
    input clk,rst,load;
    input [0:3]din;
    output [0:3]count;
    reg[0:3]count;

        always@(posedge clk or negedge rst)begin
                if(rst)
                    count <= 4'd0;
                else if(load)
                    count <= din;
                else if(count < 4'd10)
                    count <= count + 4'd1;
        end

endmodule
*/
///////////////////////////////////////////////////////////////////////////////////////////////////
/*
Bugs :
    1) The msb and lsb representation of din and count is reveresed i.e. [0:3]din and [0:3]count, 
       must be changed to [3:0]din and [3:0]count
    2) Incomplete logic of mod10 counter i.e. if the count value is greater than 10,
       then the count output must be set to zero 
    3) Incorrect logic of negedge reset which should be corrected to: if(!rst) then count<=4'd0
    4) Incorrect condition for increment logic of count : count<4'd9
    5) Here, when load is high din can be given in the range 0 to 15, 
       as it is a mod10 counter the count value is valid to hold value from 0 to 9, hence load logic is incorrect  
*/

//MODIFIED CODE OF MOD10COUNTER:
module mod10counter (clk,rst,count,load,din);
    input clk,rst,load;
    input [3:0]din;             //Corrected
    output [3:0]count;          //Corrected
    reg[3:0]count;              //Corrected

        always@(posedge clk or negedge rst)begin
                if(!rst)          //Corrected
                    count <= 4'd0;
                else if(load)begin     //Corrected
                    if(din < 4'd10)
                        count <= din;
                    else
                        count <=4'd0;
                end
                else if(count < 4'd9)  //Corrected
                    count <= count + 4'd1;
                else                    //Introduced
                    count <=4'd0;       //Introduced
        end

endmodule

TEST_Folder/mod10counter_test.v
`timescale 1ns/1ns

module mod10counter_test();
    reg clk;
    reg rst;
    reg load;
    reg [3:0]din;
    wire [3:0]count;    
    
    //Variables used for scoreboard:
    integer error;
    integer correct;
    //error=0;
    //correct=0;

    //Model instantioation
    mod10counter dut(.clk(clk), .rst(rst), .count(count), .load(load), .din(din));

    //clock generation :
    always #5 clk = ~clk;

    //Stimulus generation :
    initial begin
        error = 0;
        correct = 0;
        clk = 0;
        rst = 1'b0;
        load = 1'b0;
        din = 4'd10;
        #20; rst = 1'b1;
        //Count upto 9 and then fall back to count value to 0:
        #130; rst = 1'b0;
        //varing load value to check all worst cases of output:
        repeat(150)begin
            #30; load = ~load;
            #10; din = din + 1'b1;
        end
        //Randomize the input signal:
        repeat(200)begin
            rst = $random;
            load = $random;
            din = $random;
            #20;
        end
        #20; rst = 1'b0;
        #10;$finish;
    end

    //Simulation waveform:
    initial begin
        $dumpfile("mod10counter_wave.vcd");
        $dumpvars(0,mod10counter_test);
    end

    //Scoreboard evaluation :
        always@(posedge clk or negedge rst) begin
            //Testcase 1 : Reset high check count equal to zero
            if (rst == 1'b0)begin
			    if(count == 4'b0)
				    correct=correct+1;
			    else begin
                		error=error+1;
                		$display("ERROR!!! Testcase 1 : Reset high check count equal to zero");
            	end
    	    end
            //Testcase 2: Check count value (greater than or equal to 0) or (less than 10) 
            if (count >=4'd0) begin
			    if(count < 4'd10)
				    correct=correct+1;
			    else begin
              			error=error+1;
                		$display("ERROR!!! Testcase 2: Check count value (greater than or equal to 0) or (less than 10)");
            	end
	        end
            //Testcase 3: Load high or Low, din>10 or din<10, count == 4'b0 or count<4'd10
            if(load == 1'b1 && din>=4'd10)begin
			    if(count==4'd0)
				    correct=correct+1;
			    else begin
                		error=error+1;
                		$display("ERROR!!! Testcase 3_1: Load high , din>10, count == 4'b0");
            	end
	        end
	        else if(load == 1'b1 && din<4'd10)begin
			    if(count<4'd10)
				    correct=correct+1;
			    else begin
                		error=error+1;
                		$display("ERROR!!! Testcase 3_2: Load high , din<10, count < 4'b10");
            	end			
	        end
	        else begin
			    if(load == 1'b0)begin
				    if(count<4'd10)
					    correct=correct+1;
				    else begin
                			error=error+1;
                			$display("ERROR!!! Testcase 3_3: Load low ,count < 4'b10");
            	    end
			    end	
	        end
        end

    //Display output:
    initial begin
        $monitor("Rst=%b|Load=%b|Count=%d ||| Correct=%d | Error = %d",rst,load,count,correct,error); 
    end    

    endmodule

TEST_Folder/mod10counter_wave.vcd
$date
	Tue Feb 10 10:36:38 2026
$end
$version
	Icarus Verilog
$end
$timescale
	1ns
$end
$scope module mod10counter_test $end
$var wire 4 ! count [3:0] $end
$var reg 1 " clk $end
$var reg 4 # din [3:0] $end
$var reg 1 $ load $end
$var reg 1 % rst $end
$var integer 32 & correct [31:0] $end
$var integer 32 ' error [31:0] $end
$scope module dut $end
$var wire 1 " clk $end
$var wire 4 ( din [3:0] $end
$var wire 1 $ load $end
$var wire 1 % rst $end
$var reg 4 ) count [3:0] $end
$upscope $end
$upscope $end
$enddefinitions $end
$comment Show the parameter values. $end
$dumpall
$end
#0
$dumpvars
b0 )
b1010 (
b0 '
b0 &
0%
0$
b1010 #
0"
b0 !
$end
#5
b11 &
1"
#10
0"
#15
b110 &
1"
#20
0"
1%
#25
b1 !
b1 )
b1000 &
1"
#30
0"
#35
b10 !
b10 )
b1010 &
1"
#40
0"
#45
b11 !
b11 )
b1100 &
1"
#50
0"
#55
b100 !
b100 )
b1110 &
1"
#60
0"
#65
b101 !
b101 )
b10000 &
1"
#70
0"
#75
b110 !
b110 )
b10010 &
1"
#80
0"
#85
b111 !
b111 )
b10100 &
1"
#90
0"
#95
b1000 !
b1000 )
b10110 &
1"
#100
0"
#105
b1001 !
b1001 )
b11000 &
1"
#110
0"
#115
b0 !
b0 )
b11010 &
1"
#120
0"
#125
b1 !
b1 )
b11100 &
1"
#130
0"
#135
b10 !
b10 )
b11110 &
1"
#140
0"
#145
b11 !
b11 )
b100000 &
1"
#150
b0 !
b0 )
b100010 &
b1 '
0"
0%
#155
b100101 &
1"
#160
0"
#165
b101000 &
1"
#170
0"
#175
b101011 &
1"
#180
0"
1$
#185
b101110 &
1"
#190
0"
b1011 #
b1011 (
#195
b110001 &
1"
#200
0"
#205
b110100 &
1"
#210
0"
#215
b110111 &
1"
#220
0"
0$
#225
b111010 &
1"
#230
0"
b1100 #
b1100 (
#235
b111101 &
1"
#240
0"
#245
b1000000 &
1"
#250
0"
#255
b1000011 &
1"
#260
0"
1$
#265
b1000110 &
1"
#270
0"
b1101 #
b1101 (
#275
b1001001 &
1"
#280
0"
#285
b1001100 &
1"
#290
0"
#295
b1001111 &
1"
#300
0"
0$
#305
b1010010 &
1"
#310
0"
b1110 #
b1110 (
#315
b1010101 &
1"
#320
0"
#325
b1011000 &
1"
#330
0"
#335
b1011011 &
1"
#340
0"
1$
#345
b1011110 &
1"
#350
0"
b1111 #
b1111 (
#355
b1100001 &
1"
#360
0"
#365
b1100100 &
1"
#370
0"
#375
b1100111 &
1"
#380
0"
0$
#385
b1101010 &
1"
#390
0"
b0 #
b0 (
#395
b1101101 &
1"
#400
0"
#405
b1110000 &
1"
#410
0"
#415
b1110011 &
1"
#420
0"
1$
#425
b1110110 &
1"
#430
0"
b1 #
b1 (
#435
b1111001 &
1"
#440
0"
#445
b1111100 &
1"
#450
0"
#455
b1111111 &
1"
#460
0"
0$
#465
b10000010 &
1"
#470
0"
b10 #
b10 (
#475
b10000101 &
1"
#480
0"
#485
b10001000 &
1"
#490
0"
#495
b10001011 &
1"
#500
0"
1$
#505
b10001110 &
1"
#510
0"
b11 #
b11 (
#515
b10010001 &
1"
#520
0"
#525
b10010100 &
1"
#530
0"
#535
b10010111 &
1"
#540
0"
0$
#545
b10011010 &
1"
#550
0"
b100 #
b100 (
#555
b10011101 &
1"
#560
0"
#565
b10100000 &
1"
#570
0"
#575
b10100011 &
1"
#580
0"
1$
#585
b10100110 &
1"
#590
0"
b101 #
b101 (
#595
b10101001 &
1"
#600
0"
#605
b10101100 &
1"
#610
0"
#615
b10101111 &
1"
#620
0"
0$
#625
b10110010 &
1"
#630
0"
b110 #
b110 (
#635
b10110101 &
1"
#640
0"
#645
b10111000 &
1"
#650
0"
#655
b10111011 &
1"
#660
0"
1$
#665
b10111110 &
1"
#670
0"
b111 #
b111 (
#675
b11000001 &
1"
#680
0"
#685
b11000100 &
1"
#690
0"
#695
b11000111 &
1"
#700
0"
0$
#705
b11001010 &
1"
#710
0"
b1000 #
b1000 (
#715
b11001101 &
1"
#720
0"
#725
b11010000 &
1"
#730
0"
#735
b11010011 &
1"
#740
0"
1$
#745
b11010110 &
1"
#750
0"
b1001 #
b1001 (
#755
b11011001 &
1"
#760
0"
#765
b11011100 &
1"
#770
0"
#775
b11011111 &
1"
#780
0"
0$
#785
b11100010 &
1"
#790
0"
b1010 #
b1010 (
#795
b11100101 &
1"
#800
0"
#805
b11101000 &
1"
#810
0"
#815
b11101011 &
1"
#820
0"
1$
#825
b11101110 &
1"
#830
0"
b1011 #
b1011 (
#835
b11110001 &
1"
#840
0"
#845
b11110100 &
1"
#850
0"
#855
b11110111 &
1"
#860
0"
0$
#865
b11111010 &
1"
#870
0"
b1100 #
b1100 (
#875
b11111101 &
1"
#880
0"
#885
b100000000 &
1"
#890
0"
#895
b100000011 &
1"
#900
0"
1$
#905
b100000110 &
1"
#910
0"
b1101 #
b1101 (
#915
b100001001 &
1"
#920
0"
#925
b100001100 &
1"
#930
0"
#935
b100001111 &
1"
#940
0"
0$
#945
b100010010 &
1"
#950
0"
b1110 #
b1110 (
#955
b100010101 &
1"
#960
0"
#965
b100011000 &
1"
#970
0"
#975
b100011011 &
1"
#980
0"
1$
#985
b100011110 &
1"
#990
0"
b1111 #
b1111 (
#995
b100100001 &
1"
#1000
0"
#1005
b100100100 &
1"
#1010
0"
#1015
b100100111 &
1"
#1020
0"
0$
#1025
b100101010 &
1"
#1030
0"
b0 #
b0 (
#1035
b100101101 &
1"
#1040
0"
#1045
b100110000 &
1"
#1050
0"
#1055
b100110011 &
1"
#1060
0"
1$
#1065
b100110110 &
1"
#1070
0"
b1 #
b1 (
#1075
b100111001 &
1"
#1080
0"
#1085
b100111100 &
1"
#1090
0"
#1095
b100111111 &
1"
#1100
0"
0$
#1105
b101000010 &
1"
#1110
0"
b10 #
b10 (
#1115
b101000101 &
1"
#1120
0"
#1125
b101001000 &
1"
#1130
0"
#1135
b101001011 &
1"
#1140
0"
1$
#1145
b101001110 &
1"
#1150
0"
b11 #
b11 (
#1155
b101010001 &
1"
#1160
0"
#1165
b101010100 &
1"
#1170
0"
#1175
b101010111 &
1"
#1180
0"
0$
#1185
b101011010 &
1"
#1190
0"
b100 #
b100 (
#1195
b101011101 &
1"
#1200
0"
#1205
b101100000 &
1"
#1210
0"
#1215
b101100011 &
1"
#1220
0"
1$
#1225
b101100110 &
1"
#1230
0"
b101 #
b101 (
#1235
b101101001 &
1"
#1240
0"
#1245
b101101100 &
1"
#1250
0"
#1255
b101101111 &
1"
#1260
0"
0$
#1265
b101110010 &
1"
#1270
0"
b110 #
b110 (
#1275
b101110101 &
1"
#1280
0"
#1285
b101111000 &
1"
#1290
0"
#1295
b101111011 &
1"
#1300
0"
1$
#1305
b101111110 &
1"
#1310
0"
b111 #
b111 (
#1315
b110000001 &
1"
#1320
0"
#1325
b110000100 &
1"
#1330
0"
#1335
b110000111 &
1"
#1340
0"
0$
#1345
b110001010 &
1"
#1350
0"
b1000 #
b1000 (
#1355
b110001101 &
1"
#1360
0"
#1365
b110010000 &
1"
#1370
0"
#1375
b110010011 &
1"
#1380
0"
1$
#1385
b110010110 &
1"
#1390
0"
b1001 #
b1001 (
#1395
b110011001 &
1"
#1400
0"
#1405
b110011100 &
1"
#1410
0"
#1415
b110011111 &
1"
#1420
0"
0$
#1425
b110100010 &
1"
#1430
0"
b1010 #
b1010 (
#1435
b110100101 &
1"
#1440
0"
#1445
b110101000 &
1"
#1450
0"
#1455
b110101011 &
1"
#1460
0"
1$
#1465
b110101110 &
1"
#1470
0"
b1011 #
b1011 (
#1475
b110110001 &
1"
#1480
0"
#1485
b110110100 &
1"
#1490
0"
#1495
b110110111 &
1"
#1500
0"
0$
#1505
b110111010 &
1"
#1510
0"
b1100 #
b1100 (
#1515
b110111101 &
1"
#1520
0"
#1525
b111000000 &
1"
#1530
0"
#1535
b111000011 &
1"
#1540
0"
1$
#1545
b111000110 &
1"
#1550
0"
b1101 #
b1101 (
#1555
b111001001 &
1"
#1560
0"
#1565
b111001100 &
1"
#1570
0"
#1575
b111001111 &
1"
#1580
0"
0$
#1585
b111010010 &
1"
#1590
0"
b1110 #
b1110 (
#1595
b111010101 &
1"
#1600
0"
#1605
b111011000 &
1"
#1610
0"
#1615
b111011011 &
1"
#1620
0"
1$
#1625
b111011110 &
1"
#1630
0"
b1111 #
b1111 (
#1635
b111100001 &
1"
#1640
0"
#1645
b111100100 &
1"
#1650
0"
#1655
b111100111 &
1"
#1660
0"
0$
#1665
b111101010 &
1"
#1670
0"
b0 #
b0 (
#1675
b111101101 &
1"
#1680
0"
#1685
b111110000 &
1"
#1690
0"
#1695
b111110011 &
1"
#1700
0"
1$
#1705
b111110110 &
1"
#1710
0"
b1 #
b1 (
#1715
b111111001 &
1"
#1720
0"
#1725
b111111100 &
1"
#1730
0"
#1735
b111111111 &
1"
#1740
0"
0$
#1745
b1000000010 &
1"
#1750
0"
b10 #
b10 (
#1755
b1000000101 &
1"
#1760
0"
#1765
b1000001000 &
1"
#1770
0"
#1775
b1000001011 &
1"
#1780
0"
1$
#1785
b1000001110 &
1"
#1790
0"
b11 #
b11 (
#1795
b1000010001 &
1"
#1800
0"
#1805
b1000010100 &
1"
#1810
0"
#1815
b1000010111 &
1"
#1820
0"
0$
#1825
b1000011010 &
1"
#1830
0"
b100 #
b100 (
#1835
b1000011101 &
1"
#1840
0"
#1845
b1000100000 &
1"
#1850
0"
#1855
b1000100011 &
1"
#1860
0"
1$
#1865
b1000100110 &
1"
#1870
0"
b101 #
b101 (
#1875
b1000101001 &
1"
#1880
0"
#1885
b1000101100 &
1"
#1890
0"
#1895
b1000101111 &
1"
#1900
0"
0$
#1905
b1000110010 &
1"
#1910
0"
b110 #
b110 (
#1915
b1000110101 &
1"
#1920
0"
#1925
b1000111000 &
1"
#1930
0"
#1935
b1000111011 &
1"
#1940
0"
1$
#1945
b1000111110 &
1"
#1950
0"
b111 #
b111 (
#1955
b1001000001 &
1"
#1960
0"
#1965
b1001000100 &
1"
#1970
0"
#1975
b1001000111 &
1"
#1980
0"
0$
#1985
b1001001010 &
1"
#1990
0"
b1000 #
b1000 (
#1995
b1001001101 &
1"
#2000
0"
#2005
b1001010000 &
1"
#2010
0"
#2015
b1001010011 &
1"
#2020
0"
1$
#2025
b1001010110 &
1"
#2030
0"
b1001 #
b1001 (
#2035
b1001011001 &
1"
#2040
0"
#2045
b1001011100 &
1"
#2050
0"
#2055
b1001011111 &
1"
#2060
0"
0$
#2065
b1001100010 &
1"
#2070
0"
b1010 #
b1010 (
#2075
b1001100101 &
1"
#2080
0"
#2085
b1001101000 &
1"
#2090
0"
#2095
b1001101011 &
1"
#2100
0"
1$
#2105
b1001101110 &
1"
#2110
0"
b1011 #
b1011 (
#2115
b1001110001 &
1"
#2120
0"
#2125
b1001110100 &
1"
#2130
0"
#2135
b1001110111 &
1"
#2140
0"
0$
#2145
b1001111010 &
1"
#2150
0"
b1100 #
b1100 (
#2155
b1001111101 &
1"
#2160
0"
#2165
b1010000000 &
1"
#2170
0"
#2175
b1010000011 &
1"
#2180
0"
1$
#2185
b1010000110 &
1"
#2190
0"
b1101 #
b1101 (
#2195
b1010001001 &
1"
#2200
0"
#2205
b1010001100 &
1"
#2210
0"
#2215
b1010001111 &
1"
#2220
0"
0$
#2225
b1010010010 &
1"
#2230
0"
b1110 #
b1110 (
#2235
b1010010101 &
1"
#2240
0"
#2245
b1010011000 &
1"
#2250
0"
#2255
b1010011011 &
1"
#2260
0"
1$
#2265
b1010011110 &
1"
#2270
0"
b1111 #
b1111 (
#2275
b1010100001 &
1"
#2280
0"
#2285
b1010100100 &
1"
#2290
0"
#2295
b1010100111 &
1"
#2300
0"
0$
#2305
b1010101010 &
1"
#2310
0"
b0 #
b0 (
#2315
b1010101101 &
1"
#2320
0"
#2325
b1010110000 &
1"
#2330
0"
#2335
b1010110011 &
1"
#2340
0"
1$
#2345
b1010110110 &
1"
#2350
0"
b1 #
b1 (
#2355
b1010111001 &
1"
#2360
0"
#2365
b1010111100 &
1"
#2370
0"
#2375
b1010111111 &
1"
#2380
0"
0$
#2385
b1011000010 &
1"
#2390
0"
b10 #
b10 (
#2395
b1011000101 &
1"
#2400
0"
#2405
b1011001000 &
1"
#2410
0"
#2415
b1011001011 &
1"
#2420
0"
1$
#2425
b1011001110 &
1"
#2430
0"
b11 #
b11 (
#2435
b1011010001 &
1"
#2440
0"
#2445
b1011010100 &
1"
#2450
0"
#2455
b1011010111 &
1"
#2460
0"
0$
#2465
b1011011010 &
1"
#2470
0"
b100 #
b100 (
#2475
b1011011101 &
1"
#2480
0"
#2485
b1011100000 &
1"
#2490
0"
#2495
b1011100011 &
1"
#2500
0"
1$
#2505
b1011100110 &
1"
#2510
0"
b101 #
b101 (
#2515
b1011101001 &
1"
#2520
0"
#2525
b1011101100 &
1"
#2530
0"
#2535
b1011101111 &
1"
#2540
0"
0$
#2545
b1011110010 &
1"
#2550
0"
b110 #
b110 (
#2555
b1011110101 &
1"
#2560
0"
#2565
b1011111000 &
1"
#2570
0"
#2575
b1011111011 &
1"
#2580
0"
1$
#2585
b1011111110 &
1"
#2590
0"
b111 #
b111 (
#2595
b1100000001 &
1"
#2600
0"
#2605
b1100000100 &
1"
#2610
0"
#2615
b1100000111 &
1"
#2620
0"
0$
#2625
b1100001010 &
1"
#2630
0"
b1000 #
b1000 (
#2635
b1100001101 &
1"
#2640
0"
#2645
b1100010000 &
1"
#2650
0"
#2655
b1100010011 &
1"
#2660
0"
1$
#2665
b1100010110 &
1"
#2670
0"
b1001 #
b1001 (
#2675
b1100011001 &
1"
#2680
0"
#2685
b1100011100 &
1"
#2690
0"
#2695
b1100011111 &
1"
#2700
0"
0$
#2705
b1100100010 &
1"
#2710
0"
b1010 #
b1010 (
#2715
b1100100101 &
1"
#2720
0"
#2725
b1100101000 &
1"
#2730
0"
#2735
b1100101011 &
1"
#2740
0"
1$
#2745
b1100101110 &
1"
#2750
0"
b1011 #
b1011 (
#2755
b1100110001 &
1"
#2760
0"
#2765
b1100110100 &
1"
#2770
0"
#2775
b1100110111 &
1"
#2780
0"
0$
#2785
b1100111010 &
1"
#2790
0"
b1100 #
b1100 (
#2795
b1100111101 &
1"
#2800
0"
#2805
b1101000000 &
1"
#2810
0"
#2815
b1101000011 &
1"
#2820
0"
1$
#2825
b1101000110 &
1"
#2830
0"
b1101 #
b1101 (
#2835
b1101001001 &
1"
#2840
0"
#2845
b1101001100 &
1"
#2850
0"
#2855
b1101001111 &
1"
#2860
0"
0$
#2865
b1101010010 &
1"
#2870
0"
b1110 #
b1110 (
#2875
b1101010101 &
1"
#2880
0"
#2885
b1101011000 &
1"
#2890
0"
#2895
b1101011011 &
1"
#2900
0"
1$
#2905
b1101011110 &
1"
#2910
0"
b1111 #
b1111 (
#2915
b1101100001 &
1"
#2920
0"
#2925
b1101100100 &
1"
#2930
0"
#2935
b1101100111 &
1"
#2940
0"
0$
#2945
b1101101010 &
1"
#2950
0"
b0 #
b0 (
#2955
b1101101101 &
1"
#2960
0"
#2965
b1101110000 &
1"
#2970
0"
#2975
b1101110011 &
1"
#2980
0"
1$
#2985
b1101110110 &
1"
#2990
0"
b1 #
b1 (
#2995
b1101111001 &
1"
#3000
0"
#3005
b1101111100 &
1"
#3010
0"
#3015
b1101111111 &
1"
#3020
0"
0$
#3025
b1110000010 &
1"
#3030
0"
b10 #
b10 (
#3035
b1110000101 &
1"
#3040
0"
#3045
b1110001000 &
1"
#3050
0"
#3055
b1110001011 &
1"
#3060
0"
1$
#3065
b1110001110 &
1"
#3070
0"
b11 #
b11 (
#3075
b1110010001 &
1"
#3080
0"
#3085
b1110010100 &
1"
#3090
0"
#3095
b1110010111 &
1"
#3100
0"
0$
#3105
b1110011010 &
1"
#3110
0"
b100 #
b100 (
#3115
b1110011101 &
1"
#3120
0"
#3125
b1110100000 &
1"
#3130
0"
#3135
b1110100011 &
1"
#3140
0"
1$
#3145
b1110100110 &
1"
#3150
0"
b101 #
b101 (
#3155
b1110101001 &
1"
#3160
0"
#3165
b1110101100 &
1"
#3170
0"
#3175
b1110101111 &
1"
#3180
0"
0$
#3185
b1110110010 &
1"
#3190
0"
b110 #
b110 (
#3195
b1110110101 &
1"
#3200
0"
#3205
b1110111000 &
1"
#3210
0"
#3215
b1110111011 &
1"
#3220
0"
1$
#3225
b1110111110 &
1"
#3230
0"
b111 #
b111 (
#3235
b1111000001 &
1"
#3240
0"
#3245
b1111000100 &
1"
#3250
0"
#3255
b1111000111 &
1"
#3260
0"
0$
#3265
b1111001010 &
1"
#3270
0"
b1000 #
b1000 (
#3275
b1111001101 &
1"
#3280
0"
#3285
b1111010000 &
1"
#3290
0"
#3295
b1111010011 &
1"
#3300
0"
1$
#3305
b1111010110 &
1"
#3310
0"
b1001 #
b1001 (
#3315
b1111011001 &
1"
#3320
0"
#3325
b1111011100 &
1"
#3330
0"
#3335
b1111011111 &
1"
#3340
0"
0$
#3345
b1111100010 &
1"
#3350
0"
b1010 #
b1010 (
#3355
b1111100101 &
1"
#3360
0"
#3365
b1111101000 &
1"
#3370
0"
#3375
b1111101011 &
1"
#3380
0"
1$
#3385
b1111101110 &
1"
#3390
0"
b1011 #
b1011 (
#3395
b1111110001 &
1"
#3400
0"
#3405
b1111110100 &
1"
#3410
0"
#3415
b1111110111 &
1"
#3420
0"
0$
#3425
b1111111010 &
1"
#3430
0"
b1100 #
b1100 (
#3435
b1111111101 &
1"
#3440
0"
#3445
b10000000000 &
1"
#3450
0"
#3455
b10000000011 &
1"
#3460
0"
1$
#3465
b10000000110 &
1"
#3470
0"
b1101 #
b1101 (
#3475
b10000001001 &
1"
#3480
0"
#3485
b10000001100 &
1"
#3490
0"
#3495
b10000001111 &
1"
#3500
0"
0$
#3505
b10000010010 &
1"
#3510
0"
b1110 #
b1110 (
#3515
b10000010101 &
1"
#3520
0"
#3525
b10000011000 &
1"
#3530
0"
#3535
b10000011011 &
1"
#3540
0"
1$
#3545
b10000011110 &
1"
#3550
0"
b1111 #
b1111 (
#3555
b10000100001 &
1"
#3560
0"
#3565
b10000100100 &
1"
#3570
0"
#3575
b10000100111 &
1"
#3580
0"
0$
#3585
b10000101010 &
1"
#3590
0"
b0 #
b0 (
#3595
b10000101101 &
1"
#3600
0"
#3605
b10000110000 &
1"
#3610
0"
#3615
b10000110011 &
1"
#3620
0"
1$
#3625
b10000110110 &
1"
#3630
0"
b1 #
b1 (
#3635
b10000111001 &
1"
#3640
0"
#3645
b10000111100 &
1"
#3650
0"
#3655
b10000111111 &
1"
#3660
0"
0$
#3665
b10001000010 &
1"
#3670
0"
b10 #
b10 (
#3675
b10001000101 &
1"
#3680
0"
#3685
b10001001000 &
1"
#3690
0"
#3695
b10001001011 &
1"
#3700
0"
1$
#3705
b10001001110 &
1"
#3710
0"
b11 #
b11 (
#3715
b10001010001 &
1"
#3720
0"
#3725
b10001010100 &
1"
#3730
0"
#3735
b10001010111 &
1"
#3740
0"
0$
#3745
b10001011010 &
1"
#3750
0"
b100 #
b100 (
#3755
b10001011101 &
1"
#3760
0"
#3765
b10001100000 &
1"
#3770
0"
#3775
b10001100011 &
1"
#3780
0"
1$
#3785
b10001100110 &
1"
#3790
0"
b101 #
b101 (
#3795
b10001101001 &
1"
#3800
0"
#3805
b10001101100 &
1"
#3810
0"
#3815
b10001101111 &
1"
#3820
0"
0$
#3825
b10001110010 &
1"
#3830
0"
b110 #
b110 (
#3835
b10001110101 &
1"
#3840
0"
#3845
b10001111000 &
1"
#3850
0"
#3855
b10001111011 &
1"
#3860
0"
1$
#3865
b10001111110 &
1"
#3870
0"
b111 #
b111 (
#3875
b10010000001 &
1"
#3880
0"
#3885
b10010000100 &
1"
#3890
0"
#3895
b10010000111 &
1"
#3900
0"
0$
#3905
b10010001010 &
1"
#3910
0"
b1000 #
b1000 (
#3915
b10010001101 &
1"
#3920
0"
#3925
b10010010000 &
1"
#3930
0"
#3935
b10010010011 &
1"
#3940
0"
1$
#3945
b10010010110 &
1"
#3950
0"
b1001 #
b1001 (
#3955
b10010011001 &
1"
#3960
0"
#3965
b10010011100 &
1"
#3970
0"
#3975
b10010011111 &
1"
#3980
0"
0$
#3985
b10010100010 &
1"
#3990
0"
b1010 #
b1010 (
#3995
b10010100101 &
1"
#4000
0"
#4005
b10010101000 &
1"
#4010
0"
#4015
b10010101011 &
1"
#4020
0"
1$
#4025
b10010101110 &
1"
#4030
0"
b1011 #
b1011 (
#4035
b10010110001 &
1"
#4040
0"
#4045
b10010110100 &
1"
#4050
0"
#4055
b10010110111 &
1"
#4060
0"
0$
#4065
b10010111010 &
1"
#4070
0"
b1100 #
b1100 (
#4075
b10010111101 &
1"
#4080
0"
#4085
b10011000000 &
1"
#4090
0"
#4095
b10011000011 &
1"
#4100
0"
1$
#4105
b10011000110 &
1"
#4110
0"
b1101 #
b1101 (
#4115
b10011001001 &
1"
#4120
0"
#4125
b10011001100 &
1"
#4130
0"
#4135
b10011001111 &
1"
#4140
0"
0$
#4145
b10011010010 &
1"
#4150
0"
b1110 #
b1110 (
#4155
b10011010101 &
1"
#4160
0"
#4165
b10011011000 &
1"
#4170
0"
#4175
b10011011011 &
1"
#4180
0"
1$
#4185
b10011011110 &
1"
#4190
0"
b1111 #
b1111 (
#4195
b10011100001 &
1"
#4200
0"
#4205
b10011100100 &
1"
#4210
0"
#4215
b10011100111 &
1"
#4220
0"
0$
#4225
b10011101010 &
1"
#4230
0"
b0 #
b0 (
#4235
b10011101101 &
1"
#4240
0"
#4245
b10011110000 &
1"
#4250
0"
#4255
b10011110011 &
1"
#4260
0"
1$
#4265
b10011110110 &
1"
#4270
0"
b1 #
b1 (
#4275
b10011111001 &
1"
#4280
0"
#4285
b10011111100 &
1"
#4290
0"
#4295
b10011111111 &
1"
#4300
0"
0$
#4305
b10100000010 &
1"
#4310
0"
b10 #
b10 (
#4315
b10100000101 &
1"
#4320
0"
#4325
b10100001000 &
1"
#4330
0"
#4335
b10100001011 &
1"
#4340
0"
1$
#4345
b10100001110 &
1"
#4350
0"
b11 #
b11 (
#4355
b10100010001 &
1"
#4360
0"
#4365
b10100010100 &
1"
#4370
0"
#4375
b10100010111 &
1"
#4380
0"
0$
#4385
b10100011010 &
1"
#4390
0"
b100 #
b100 (
#4395
b10100011101 &
1"
#4400
0"
#4405
b10100100000 &
1"
#4410
0"
#4415
b10100100011 &
1"
#4420
0"
1$
#4425
b10100100110 &
1"
#4430
0"
b101 #
b101 (
#4435
b10100101001 &
1"
#4440
0"
#4445
b10100101100 &
1"
#4450
0"
#4455
b10100101111 &
1"
#4460
0"
0$
#4465
b10100110010 &
1"
#4470
0"
b110 #
b110 (
#4475
b10100110101 &
1"
#4480
0"
#4485
b10100111000 &
1"
#4490
0"
#4495
b10100111011 &
1"
#4500
0"
1$
#4505
b10100111110 &
1"
#4510
0"
b111 #
b111 (
#4515
b10101000001 &
1"
#4520
0"
#4525
b10101000100 &
1"
#4530
0"
#4535
b10101000111 &
1"
#4540
0"
0$
#4545
b10101001010 &
1"
#4550
0"
b1000 #
b1000 (
#4555
b10101001101 &
1"
#4560
0"
#4565
b10101010000 &
1"
#4570
0"
#4575
b10101010011 &
1"
#4580
0"
1$
#4585
b10101010110 &
1"
#4590
0"
b1001 #
b1001 (
#4595
b10101011001 &
1"
#4600
0"
#4605
b10101011100 &
1"
#4610
0"
#4615
b10101011111 &
1"
#4620
0"
0$
#4625
b10101100010 &
1"
#4630
0"
b1010 #
b1010 (
#4635
b10101100101 &
1"
#4640
0"
#4645
b10101101000 &
1"
#4650
0"
#4655
b10101101011 &
1"
#4660
0"
1$
#4665
b10101101110 &
1"
#4670
0"
b1011 #
b1011 (
#4675
b10101110001 &
1"
#4680
0"
#4685
b10101110100 &
1"
#4690
0"
#4695
b10101110111 &
1"
#4700
0"
0$
#4705
b10101111010 &
1"
#4710
0"
b1100 #
b1100 (
#4715
b10101111101 &
1"
#4720
0"
#4725
b10110000000 &
1"
#4730
0"
#4735
b10110000011 &
1"
#4740
0"
1$
#4745
b10110000110 &
1"
#4750
0"
b1101 #
b1101 (
#4755
b10110001001 &
1"
#4760
0"
#4765
b10110001100 &
1"
#4770
0"
#4775
b10110001111 &
1"
#4780
0"
0$
#4785
b10110010010 &
1"
#4790
0"
b1110 #
b1110 (
#4795
b10110010101 &
1"
#4800
0"
#4805
b10110011000 &
1"
#4810
0"
#4815
b10110011011 &
1"
#4820
0"
1$
#4825
b10110011110 &
1"
#4830
0"
b1111 #
b1111 (
#4835
b10110100001 &
1"
#4840
0"
#4845
b10110100100 &
1"
#4850
0"
#4855
b10110100111 &
1"
#4860
0"
0$
#4865
b10110101010 &
1"
#4870
0"
b0 #
b0 (
#4875
b10110101101 &
1"
#4880
0"
#4885
b10110110000 &
1"
#4890
0"
#4895
b10110110011 &
1"
#4900
0"
1$
#4905
b10110110110 &
1"
#4910
0"
b1 #
b1 (
#4915
b10110111001 &
1"
#4920
0"
#4925
b10110111100 &
1"
#4930
0"
#4935
b10110111111 &
1"
#4940
0"
0$
#4945
b10111000010 &
1"
#4950
0"
b10 #
b10 (
#4955
b10111000101 &
1"
#4960
0"
#4965
b10111001000 &
1"
#4970
0"
#4975
b10111001011 &
1"
#4980
0"
1$
#4985
b10111001110 &
1"
#4990
0"
b11 #
b11 (
#4995
b10111010001 &
1"
#5000
0"
#5005
b10111010100 &
1"
#5010
0"
#5015
b10111010111 &
1"
#5020
0"
0$
#5025
b10111011010 &
1"
#5030
0"
b100 #
b100 (
#5035
b10111011101 &
1"
#5040
0"
#5045
b10111100000 &
1"
#5050
0"
#5055
b10111100011 &
1"
#5060
0"
1$
